{"favorited": false, "contributors": null, "truncated": false, "text": "Graacias :D RT @RaHorajty051230 @JeMaZuCe buena pic de perfil de #twitter!!", "in_reply_to_status_id": 126862325662760961, "user": {"follow_request_sent": false, "profile_use_background_image": true, "profile_text_color": "F505BD", "default_profile_image": false, "id": 111919422, "profile_background_image_url_https": "https://pbs.twimg.com/profile_background_images/322905144/296403_2336879545413_1352585289_32713030_2379608_n.jpg", "verified": false, "profile_location": null, "profile_image_url_https": "https://pbs.twimg.com/profile_images/488671268107849730/KFv5AR4v_normal.jpeg", "profile_sidebar_fill_color": "030303", "entities": {"description": {"urls": []}}, "followers_count": 1605, "profile_sidebar_border_color": "5908FA", "id_str": "111919422", "profile_background_color": "220338", "listed_count": 17, "is_translation_enabled": false, "utc_offset": -25200, "statuses_count": 37262, "description": "Modelo; Ni de Bulto, Cantante; Ni en la Ducha \u2022El follow es bajo tu responsabilidad,si quiero doy followback, NO SE ANDEN CREYENDO TODOS MIS TUITS, Fin.", "friends_count": 702, "location": "Tegucigalpa, Honduras", "profile_link_color": "099C0E", "profile_image_url": "http://pbs.twimg.com/profile_images/488671268107849730/KFv5AR4v_normal.jpeg", "following": false, "geo_enabled": true, "profile_banner_url": "https://pbs.twimg.com/profile_banners/111919422/1405343282", "profile_background_image_url": "http://pbs.twimg.com/profile_background_images/322905144/296403_2336879545413_1352585289_32713030_2379608_n.jpg", "name": "La chica de humo", "lang": "es", "profile_background_tile": true, "favourites_count": 983, "screen_name": "JeMaZuCe", "notifications": false, "url": null, "created_at": "Sat Feb 06 16:04:05 +0000 2010", "contributors_enabled": false, "time_zone": "Mountain Time (US & Canada)", "protected": false, "default_profile": false, "is_translator": false}, "geo": null, "id": 126864074045784064, "favorite_count": 0, "lang": "es", "source": "<a href=\"http://twitter.com\" rel=\"nofollow\">Twitter Web Client</a>", "created_at": "Thu Oct 20 03:35:26 +0000 2011", "retweeted": false, "coordinates": null, "in_reply_to_user_id_str": "152447771", "entities": {"symbols": [], "user_mentions": [{"id": 111919422, "indices": [32, 41], "id_str": "111919422", "screen_name": "JeMaZuCe", "name": "La chica de humo"}], "hashtags": [{"indices": [65, 73], "text": "twitter"}], "urls": []}, "in_reply_to_status_id_str": "126862325662760961", "in_reply_to_screen_name": "MendSanch051230", "id_str": "126864074045784064", "place": null, "retweet_count": 0, "in_reply_to_user_id": 152447771}
